{
  "type": "integer",
  "title": "varno",
  "enum": [
    3,
    4,
    1,
    57,
    29,
    9,
    58,
    2,
    59,
    39,
    40,
    11,
    30,
    60,
    61,
    62,
    63,
    64,
    65,
    66,
    67,
    68,
    69,
    70,
    71,
    72,
    73,
    74,
    75,
    76,
    77,
    78,
    79,
    80,
    81,
    82,
    83,
    84,
    85,
    86,
    87,
    88,
    89,
    90,
    91,
    92,
    110,
    111,
    112,
    119,
    120,
    121,
    122,
    5,
    6,
    41,
    42,
    19,
    123,
    124,
    125,
    7,
    126,
    127,
    8,
    56,
    206,
    156,
    215,
    160,
    130,
    12,
    192,
    128,
    162,
    187,
    174,
    163,
    181,
    182,
    183,
    184,
    185,
    175,
    176,
    177,
    178,
    179,
    180,
    201,
    211,
    195,
    186,
    188,
    189,
    190,
    191,
    202,
    203,
    222,
    220,
    221,
    193,
    194,
    223,
    224,
    225,
    226,
    227,
    228,
    107,
    108,
    109,
    218,
    219,
    229,
    230,
    231,
    233,
    235,
    241,
    242,
    243,
    244,
    245,
    247,
    248,
    249,
    250,
    253,
    257,
    258,
    259,
    260,
    261,
    262,
    263,
    265,
    266,
    267,
    268,
    269,
    270,
    271,
    272,
    273,
    274,
    275,
    196,
    197,
    236,
    237,
    238,
    239,
    280
  ],
  "options": {
    "enum_titles": [
      "3,  upper air u component",
      "4,  upper air v component",
      "1,  geopotential",
      "57, thickness",
      "29, upper air rel. humidity",
      "9,  precipitable water content",
      "58, 2m rel. humidity",
      "2,  upper air temperature (K)",
      "59, upper air dew point (K)",
      "39, 2m temperature (K)",
      "40, 2m dew point (K)",
      "11, surface temperature (K)",
      "30, pressure tendency",
      "60, past weather (w)",
      "61, present weather (ww)",
      "62, visibility",
      "63, type of high clouds (ch)",
      "64, type of middle clouds (cm)",
      "65, type of low clouds (cl)",
      "66, cloud base height (nh)",
      "67, low cloud amount (n)",
      "68, additional cloud group height (hh)",
      "69, additional cloud group type (c)",
      "70, additional cloud group amount (ns)",
      "71, snow depth",
      "72, state of ground (e)",
      "73, ground temperature (tgtg)",
      "74, special phenomena (spsp)#1",
      "75, special phenomena (spsp)#2",
      "76, ice code type (rs)",
      "77, ice thickness (eses)",
      "78, ice (is)",
      "79, original time period of rain obs. (trtr)",
      "80, 6hr rain (liquid part)",
      "81, max. temperature (jj)",
      "82, ship speed (vs)",
      "83, ship direction (ds)",
      "84, wave height",
      "85, wave period",
      "86, wave direction",
      "87, general cloud group",
      "88, rel. humidity from low clouds",
      "89, rel. humidity from middle clouds",
      "90, rel. humidity from high clouds",
      "91, total amount of clouds",
      "92, 6hr snowfall (solid part of rain)",
      "110,surface pressure",
      "111,wind direction",
      "112,wind force",
      "119,brightness temperature (K)",
      "120,raw radiance",
      "121,cloud amount from satellite",
      "122,sigma 0",
      "5,  wind shear (du)",
      "6,  wind shear (dv)",
      "41, 10m u component (m/s)",
      "42, 10m v component (m/s)",
      "19, layer rel. humidity",
      "123,cloud liquid water",
      "124,ambiguous v component",
      "125,ambiguous u component",
      "7,  specific humidity (q)",
      "126,ambiguous wind direction",
      "127,ambiguous wind speed",
      "8,  vertical speed",
      "56, virtual temperature",
      "206,layer ozone",
      "156,height",
      "215,1d-var model level (pseudo)-variable",
      "160,past weather 2 (used in synoptic maps)",
      "130,characteristic of pressure tendency (used in synoptic maps)",
      "12, sea water temperature (used in synoptic maps)",
      "192,radar reflectivity",
      "128,atmospheric path delay in satellite signal",
      "162,radio occultation bending angle",
      "187,horizontal line-of-sight wind component",
      "174,aerosol optical depth at 0.55 microns",
      "163,Limb Radiances",
      "181,grg1: no2/nox",
      "182,grg2: so2",
      "183,grg3: so",
      "184,grg4: hcho",
      "185,grg5: go3",
      "175,cloud optical depth",
      "176,Ratio of fine mode to total aerosol optical depth at 0.55 microns",
      "177,optical depth",
      "178,Aerosol reflectance multi-channel",
      "179,normalized soil moisture (0-100%)",
      "180,soil moisture",
      "201,phase of aircraft flight",
      "211,Height assignment method",
      "195,radar doppler wind",
      "186,ghg1: carbon dioxide",
      "188,ghg2: methane",
      "189,ghg3: nitrous oxide",
      "190,brightness temperature real part",
      "191,brightness temperature imaginary part",
      "202,radar rain rate",
      "203,log(radar rain rate mm/h + epsilon)",
      "222,lidar backscattering",
      "220,significant wave height (m)",
      "221,surface wind speed (m/s)",
      "193,brightness temperature for clear (K)",
      "194,brightness temperature for cloudy (K)",
      "223,binary snow cover (0: no snow / 1: presence of snow)",
      "224,ocean salinity (PSU)",
      "225,potential temperature (Kelvin)",
      "226,humidity mixing ratio (kg/kg)",
      "227,airframe icing",
      "228,turbulence index",
      "107,Station pressure (Pa)",
      "108,Mean sea-level pressure (Pa)",
      "109,Standard level pressure (Pa)",
      "218,Vertical visibility (m)",
      "219,Wind shear above and below 1st maximum wind in sonde profile (s-1)",
      "229,Total zenith delay (GPS)",
      "230,Total zenith delay error (GPS)",
      "231,Cloud top temperature (K)",
      "233,Scaled radiance",
      "235,Cloud top pressure (Pa)",
      "241,GPSRO mean frequency",
      "242,Ambiguous u-wind component (m/s)",
      "243,Ambiguous v-wind component (m/s)",
      "244,Liquid water path",
      "245,Total column water vapour",
      "247,Cloud clear fraction",
      "248,Raw brightness temperature specific to HIRS (K)",
      "249,Raw brightness temperature specific to AMSU (K)",
      "250,Raw brightness temperature specific to HIRS (K)",
      "253,Sea ice fraction",
      "257,Cloud covered fraction",
      "258,humidity_mixing_ratio]",
      "259,Radial velocity from doppler radar",
      "260,Cloud ice water",
      "261,Maximum wind gust (m/s)",
      "262,Mass density",
      "263,SFERICS number of atmospheres",
      "265,Lightning strike observation (ATDNET)",
      "266,Cloud fraction (multi-level)",
      "267,Raw brightness temperature specific to AMSR 89GHz channels (K)",
      "268,Wind shear above and below 2nd maximum wind in sonde profile",
      "269,Pressure at bottom of layer SBUV (Pa)",
      "270,Pressure at top of later SBUV (Pa)",
      "271,Total cloud cover",
      "272,Depth (m)",
      "273,Sea surface height (m)",
      "274,Raw brightness temperature specific to MWTS (K)",
      "275,Raw brightness temperature specific to MWHS (K)",
      "196,total (cloud-to-ground plus intra-cloud) lightning flash density (fl/km2/day)",
      "197,cloud-to-ground lightning flash density ( fl/km2/day)",
      "236,lidar aerosol extinction (1/m)",
      "237,lidar cloud backscatter",
      "238,lidar cloud extinction",
      "239,cloud radar reflectivity",
      "280 lidar aerosol attenuated backscatter (1/m*sr)"
    ]
  },
  "links": [
    {
      "rel": "ECMWF documentation",
      "href": "https://apps.ecmwf.int/odbgov/varno.json"
    }
  ]
}
